markswift_client/__init__.py
markswift_client/client.py
markswift_client-0.1.0.dist-info/licenses/LICENSE
markswift_client-0.1.0.dist-info/METADATA
markswift_client-0.1.0.dist-info/WHEEL
markswift_client-0.1.0.dist-info/top_level.txt
markswift_client-0.1.0.dist-info/RECORD
